{"publication_info": "DS_III_1549", "full_name": "150 - 3.48 - DS_III_1549", "informant_id": 150, "informant_last_name": "Kristensen", "informant_first_name": "Jens", "informant_full_name": "Jens (Bitte Jens) Kristensen", "order_told": 3.48, "fieldtrip": "May 1888", "fieldtrip_start_date": "1888-05-02", "fieldtrip_end_date": "1888-05-09", "places": {"place": [{"place_id": 147, "name": "Ersted", "display_name": "Ersted (place recorded)"}, {"place_id": 657, "name": "Torup", "display_name": "Torup (place mentioned)"}]}, "stories_mentioned": {"story": [{"informant_id": 235, "publication_info": "DS_III_1566", "full_name": "235 - 1.43 - DS_III_1566", "url": "data/stories/263.dfl"}, {"informant_id": 368, "publication_info": "DS_II_D_33", "full_name": "368 - 0.00 - DS_II_D_33", "url": "data/stories/513.dfl"}]}, "fielddiary_page_start": "4107b", "fielddiary_page_end": "4107b", "bibliographic_info": null, "bibliography_references": null, "annotation": "Sand drifts were a threat to many Jutlandic villages, particularly in the north. Even though older maps do not make any clear annotation of an old town north of the parsonage in Torup (which is approximately a kilometer south of the village of Torup itself), there could well have been abandoned farms in the area. It is unclear if sand movements and drifts were common in the area. Perhaps the best known structure destroyed by drifting sand in Denmark is a church in Skagen that was closed in 1795 because it had become covered by drifting sand.", "danish_manuscript": "Norden for Torup Pr\u00e6stegaard har der ligget\nen By, som hed Gammelby, der blev \u00f8de\nlagt af Sandflugt.", "english_manuscript": "North of Torup parsonage there was a town which was called Gammelby which was destroyed by sand drifts.", "danish_publication": "Norden for Torup pr\u00e6steg\u00e5rd har der ligget en by, som hed Gammelby, der blev \u00f8delagt af sandflugt.", "english_publication": "North of Torup parsonage there was a town which was called Gammelby which was destroyed by sand drifts.", "keywords": {"keyword": ["drift", "north", "parsonage", "sand", "town"]}, "etk_index": {"heading_danish": "Sagn om g\u00e5rde og byer", "heading_english": "Legends about farms and towns"}, "tango_indices": {"tango_index": [null, null]}, "genre": null}