{"publication_info": "DS_III_2228", "full_name": "416 - 0.00 - DS_III_2228", "informant_id": 416, "informant_last_name": "Jonsen", "informant_first_name": "Niels", "informant_full_name": "Niels Jonsen", "order_told": 0.0, "fieldtrip": "None recorded", "places": {"place": [{"place_id": 749, "name": "B\u00e6kke", "display_name": "B\u00e6kke (place recorded)"}, {"place_id": 749, "name": "B\u00e6kke", "display_name": "B\u00e6kke (place mentioned)"}]}, "stories_mentioned": {"story": [{"informant_id": 123, "publication_info": "DS_III_744", "full_name": "123 - 2.09 - DS_III_744", "url": "data/stories/383.dfl"}, {"informant_id": 441, "publication_info": "DS_III_2233", "full_name": "441 - 0.00 - DS_III_2233", "url": "data/stories/747.dfl"}, {"informant_id": 150, "publication_info": "DS_II_G_113", "full_name": "150 - 4.16 - DS_II_G_113", "url": "data/stories/127.dfl"}, {"informant_id": 77, "publication_info": "DS_III_2198", "full_name": "77 - 0.00 - DS_III_2198", "url": "data/stories/809.dfl"}, {"informant_id": 456, "publication_info": "DS_III_2211", "full_name": "456 - 0.00 - DS_III_2211", "url": "data/stories/436.dfl"}]}, "fielddiary_page_start": "N/A", "fielddiary_page_end": "N/A", "bibliographic_info": null, "bibliography_references": null, "annotation": null, "danish_manuscript": null, "english_manuscript": null, "danish_publication": "Den gamle Ulv gik og passede byens kr\u00e6. S\u00e5 kom han til en kj\u00e6rne fuld af penge, den stod ude i Store-mose eller Gjedsb\u00e6k mose. Men s\u00e5 kunde han ikke b\u00e6re den derfra, og han satte da hans tr\u00e6sko og hans hjordekj\u00e6p ved den og gik til B\u00e6kke efter folk. Da de kom og vilde derud, kom han til hans tr\u00e6sko og kj\u00e6p ved B\u00e6kke m\u00f8lle. Pengene st\u00e5r der da endnu, men de skal en gang findes og s\u00e5 tilh\u00f8re familien af ham, der var ved den f\u00f8rste gang.", "english_publication": "Old Ulv went and took care of the town\u2019s livestock. Then he came across a churn full of money, it was lying out in Store-mose (big swamp) or Gjedsb\u00e6k swamp. But he couldn\u2019t carry it from there, so he put his clogs and his shepherd\u2019s staff next to it, and went to B\u00e6kke to get some people to help. When they came and wanted to go out there, they came across his clogs and staff by B\u00e6kke mill. The money is still out there now, but it\u2019ll be found someday and then it will belong to the family of the man who found it first.", "keywords": {"keyword": ["churn", "clogs", "family", "mill", "money", "old", "shepherd", "store", "swamp", "town"]}, "etk_index": {"heading_danish": "Sagn om skatte", "heading_english": "Legends about treasure"}, "tango_indices": {"tango_index": [null, null, null, null, null, null]}, "genre": null}